generalized_geography/__init__.py
generalized_geography/common/__init__.py
generalized_geography/common/constants.py
generalized_geography/common/utils.py
generalized_geography/datasets/__init__.py
generalized_geography/datasets/guel.py
generalized_geography/datasets/oldict.py
generalized_geography/solver/__init__.py
generalized_geography/solver/changeable_deg.py
generalized_geography/solver/deg.py
generalized_geography/solver/dvg.py
generalized_geography/solver/rdg.py
generalized_geography-0.0.17.dist-info/METADATA
generalized_geography-0.0.17.dist-info/WHEEL
generalized_geography-0.0.17.dist-info/top_level.txt
generalized_geography-0.0.17.dist-info/RECORD
