Metadata-Version: 2.4
Name: generalized-geography
Version: 0.0.17
Summary: Generalized Geography Game Solver
Home-page: https://github.com/singrum/generalized-geography
Author: Hyomin
Author-email: miamiq0000@gmail.com
Keywords: generalized geography,word chain,game,graph theory
Classifier: Programming Language :: Python :: 3.6
Classifier: Programming Language :: Python :: 3.7
Classifier: Programming Language :: Python :: 3.8
Classifier: Programming Language :: Python :: 3.9
Requires-Python: >=3.6
Requires-Dist: networkx
Requires-Dist: matplotlib
Dynamic: author
Dynamic: author-email
Dynamic: classifier
Dynamic: description
Dynamic: description-content-type
Dynamic: home-page
Dynamic: keywords
Dynamic: requires-dist
Dynamic: requires-python
Dynamic: summary
